example/__init__.py
example/asgi.py
example/manage.py
example/settings.py
example/urls.py
example/views.py
example/wsgi.py
tests/__init__.py
tests/asgi.py
tests/manage.py
tests/settings.py
tests/urls.py
tests/wsgi.py
ws_analytics/__init__.py
ws_analytics/admin.py
ws_analytics/analytics.py
ws_analytics/apps.py
ws_analytics/helpers.py
ws_analytics/middleware.py
ws_analytics/models.py
ws_analytics/services.py
ws_analytics/sessions.py
ws_analytics/settings.py
ws_analytics/tests.py
ws_analytics/urls.py
ws_analytics/views.py
ws_analytics/migrations/0001_initial.py
ws_analytics/migrations/__init__.py
django_ws_analytics-1.0.30.dist-info/LICENSE
django_ws_analytics-1.0.30.dist-info/METADATA
django_ws_analytics-1.0.30.dist-info/WHEEL
django_ws_analytics-1.0.30.dist-info/top_level.txt
django_ws_analytics-1.0.30.dist-info/RECORD
