Metadata-Version: 2.1
Name: django-ws-analytics
Version: 1.0.30
Summary: Django WS Analytics Package
Home-page: https://github.com/windschatten-it/django-ws-analytics
Author: windschatten.it
Author-email: fabian@windschatten.it
License: MIT
License-File: LICENSE
Requires-Dist: django-user-agents >=0.4.0
Requires-Dist: django-q >=1.3.9
Requires-Dist: maxminddb >=2.5.2
